[
    {
        "race_id": "6BIGGh",
        "track": "Monza Circuit",
        "layout": "Grand Prix",
        "car_class": "DTM 1992",
        "timestamp": 1764103501000,
        "participants": [
            {
                "user_id": 66016320,
                "username": "Matthew_80",
                "start_position": 3,
                "finish_position": 1,
                "incident_points": 15,
                "total_time": 1149397,
                "results": {
                    "rating_before": 1631.538,
                    "reputation_before": 100.0,
                    "rating_change": 10.352,
                    "reputation_change": -0.851
                },
                "laps": [
                    {
                        "lap": 1,
                        "time": 121333,
                        "valid": true,
                        "position": 1,
                        "incidents": []
                    },
                    {
                        "lap": 2,
                        "time": 111991,
                        "valid": false,
                        "position": 1,
                        "incidents": [
                            "Track Limit"
                        ]
                    },
                    {
                        "lap": 3,
                        "time": 113096,
                        "valid": true,
                        "position": 1,
                        "incidents": [
                            "Contact"
                        ]
                    },
                    {
                        "lap": 4,
                        "time": 111294,
                        "valid": true,
                        "position": 1,
                        "incidents": []
                    },
                    {
                        "lap": 5,
                        "time": 117042,
                        "valid": false,
                        "position": 1,
                        "incidents": [
                            "Track Limit"
                        ]
                    },
                    {
                        "lap": 6,
                        "time": 111450,
                        "valid": false,
                        "position": 1,
                        "incidents": [
                            "Track Limit",
                            "Contact"
                        ]
                    },
                    {
                        "lap": 7,
                        "time": 118837,
                        "valid": true,
                        "position": 1,
                        "incidents": []
                    },
                    {
                        "lap": 8,
                        "time": 111722,
                        "valid": true,
                        "position": 1,
                        "incidents": []
                    },
                    {
                        "lap": 9,
                        "time": 117297,
                        "valid": true,
                        "position": 1,
                        "incidents": [
                            "Contact"
                        ]
                    },
                    {
                        "lap": 10,
                        "time": 115335,
                        "valid": true,
                        "position": 1,
                        "incidents": [
                            "Contact"
                        ]
                    }
                ],
                "new_rating": 1641.89,
                "new_rep": 99.149
            },
            {
                "user_id": 39646302,
                "username": "Johannes_33",
                "start_position": 2,
                "finish_position": 2,
                "incident_points": 8,
                "total_time": 1175634,
                "results": {
                    "rating_before": 1526.699,
                    "reputation_before": 82.534,
                    "rating_change": 1.249,
                    "reputation_change": -0.5830000000000002
                },
                "laps": [
                    {
                        "lap": 1,
                        "time": 127423,
                        "valid": true,
                        "position": 2,
                        "incidents": []
                    },
                    {
                        "lap": 2,
                        "time": 119036,
                        "valid": true,
                        "position": 2,
                        "incidents": [
                            "Contact"
                        ]
                    },
                    {
                        "lap": 3,
                        "time": 118034,
                        "valid": false,
                        "position": 2,
                        "incidents": [
                            "Track Limit"
                        ]
                    },
                    {
                        "lap": 4,
                        "time": 119003,
                        "valid": true,
                        "position": 3,
                        "incidents": []
                    },
                    {
                        "lap": 5,
                        "time": 117277,
                        "valid": true,
                        "position": 3,
                        "incidents": []
                    },
                    {
                        "lap": 6,
                        "time": 114172,
                        "valid": true,
                        "position": 2,
                        "incidents": []
                    },
                    {
                        "lap": 7,
                        "time": 115025,
                        "valid": true,
                        "position": 2,
                        "incidents": []
                    },
                    {
                        "lap": 8,
                        "time": 111529,
                        "valid": true,
                        "position": 2,
                        "incidents": [
                            "Contact"
                        ]
                    },
                    {
                        "lap": 9,
                        "time": 116684,
                        "valid": true,
                        "position": 2,
                        "incidents": []
                    },
                    {
                        "lap": 10,
                        "time": 117451,
                        "valid": false,
                        "position": 2,
                        "incidents": [
                            "Track Limit"
                        ]
                    }
                ],
                "new_rating": 1527.948,
                "new_rep": 81.951
            },
            {
                "user_id": 80618508,
                "username": "Torres_73",
                "start_position": 1,
                "finish_position": 3,
                "incident_points": 7,
                "total_time": 1186016,
                "results": {
                    "rating_before": 1478.875,
                    "reputation_before": 82.443,
                    "rating_change": -11.601,
                    "reputation_change": 0.5760000000000001
                },
                "laps": [
                    {
                        "lap": 1,
                        "time": 127562,
                        "valid": true,
                        "position": 3,
                        "incidents": []
                    },
                    {
                        "lap": 2,
                        "time": 121826,
                        "valid": true,
                        "position": 3,
                        "incidents": []
                    },
                    {
                        "lap": 3,
                        "time": 117190,
                        "valid": true,
                        "position": 3,
                        "incidents": []
                    },
                    {
                        "lap": 4,
                        "time": 114634,
                        "valid": true,
                        "position": 2,
                        "incidents": []
                    },
                    {
                        "lap": 5,
                        "time": 119013,
                        "valid": true,
                        "position": 2,
                        "incidents": []
                    },
                    {
                        "lap": 6,
                        "time": 120496,
                        "valid": false,
                        "position": 3,
                        "incidents": [
                            "Track Limit"
                        ]
                    },
                    {
                        "lap": 7,
                        "time": 117463,
                        "valid": true,
                        "position": 3,
                        "incidents": []
                    },
                    {
                        "lap": 8,
                        "time": 111860,
                        "valid": true,
                        "position": 3,
                        "incidents": []
                    },
                    {
                        "lap": 9,
                        "time": 122279,
                        "valid": true,
                        "position": 3,
                        "incidents": [
                            "Contact"
                        ]
                    },
                    {
                        "lap": 10,
                        "time": 113693,
                        "valid": true,
                        "position": 3,
                        "incidents": [
                            "Contact"
                        ]
                    }
                ],
                "new_rating": 1467.274,
                "new_rep": 83.019
            }
        ]
    }
]